niamkeltd_pylib-1.0.11.dist-info/METADATA
niamkeltd_pylib-1.0.11.dist-info/WHEEL
niamkeltd_pylib-1.0.11.dist-info/entry_points.txt
niamkeltd_pylib-1.0.11.dist-info/licenses/LICENSE
niamkeltd_pylib/__init__.py
niamkeltd_pylib/database/__init__.py
niamkeltd_pylib/database/mysql/__init__.py
niamkeltd_pylib/database/mysql/dbwrapper.py
niamkeltd_pylib/helpers/__init__.py
niamkeltd_pylib/helpers/asynchelper.py
niamkeltd_pylib/helpers/datetimehelper.py
niamkeltd_pylib/helpers/debughelper.py
niamkeltd_pylib/helpers/dictionaryhelper.py
niamkeltd_pylib/helpers/messagehelper.py
niamkeltd_pylib/models/__init__.py
niamkeltd_pylib/models/emojis.py
niamkeltd_pylib/models/exceptions/__init__.py
niamkeltd_pylib/models/exceptions/timeoutexception.py
niamkeltd_pylib/models/exceptions/transientexception.py
niamkeltd_pylib/models/weekday.py
niamkeltd_pylib-1.0.11.dist-info/RECORD
