Metadata-Version: 2.4
Name: niamkeltd_pylib
Version: 1.0.11
Summary: Niamke Ltd python library
Author-Email: Damaani Webber <damaaniwebber@gmail.com>
License-Expression: AGPL-3.0-only
License-File: LICENSE
Classifier: Programming Language :: Python :: 3
Classifier: Operating System :: OS Independent
Project-URL: Homepage, https://github.com/NiamkeSolutions/niamkeltd-python-library
Project-URL: Issues, https://github.com/NiamkeSolutions/niamkeltd-python-library/issues
Requires-Python: >=3.9
